Workbook

Sheet Table 1
A1: Table 1. IDA Country Allocations in FY25
A2: (SDR million)
D4: FY25 | I4: FY25 | N4: FY24 | S4: FY25 | X4: FY25
A5: National IDA Allocations | D5: Allocations (before FY25 set-asides and reallocations and FY24 front-/back- loading) a/ (I) | I5: Set-aside Adjustments b/ (II) | N5: FY24 Front/Back Loading c/ (III) | S5: FY25 Reallocations (IV) | X5: Final Allocations (after FY25 set-asides and reallocations and FY24 front-/back- loading) d/ (V=I+II+III+IV)
A6: Country | D6: Grants | E6: Credits | F6: PBA-SMLs e/ | G6: Total | I6: Grants | J6: Credits | K6: PBA-SMLs e/ | L6: Total | N6: Grants | O6: Credits | P6: PBA-SMLs e/ | Q6: Total | S6: Grants | T6: Credits | U6: PBA-SMLs e/ | V6: Total | X6: Grants | Y6: Credits | Z6: PBA-SMLs e/ | AA6: Total
A7: Africa Eastern and Southern
A8: Burundi | B8: f/ | D8: 183.14803 | E8: 0.0 | F8: 0 | G8: 183.14803 | I8: 0 | J8: 0 | K8: 0 | L8: 0 | N8: -6.7370498 | O8: 0 | P8: 0 | Q8: -6.7370498 | S8: 81.20278 | T8: 0 | U8: 0 | V8: 81.20278 | X8: 257.61376 | Y8: 0 | Z8: 0 | AA8: 257.61376 | AB8: =AA8/G8*100-100 -> 40.658766
A9: Comoros | D9: 18.149145 | E9: 0.0 | F9: 0 | G9: 18.149145 | I9: 0 | J9: 0 | K9: 0 | L9: 0 | N9: -14.231026 | O9: 0 | P9: 0 | Q9: -14.231026 | S9: 0 | T9: 0 | U9: 0 | V9: 0 | X9: 3.9181185 | Y9: 0 | Z9: 0 | AA9: 3.9181185 | AB9: =AA9/G9*100-100 -> -78.411553
A10: Congo, Democratic Republic of | D10: 0 | E10: 657.23989 | F10: 75.173608 | G10: 732.41349 | I10: 0 | J10: 0 | K10: 0 | L10: 0 | N10: 0 | O10: -307.61257 | P10: 218.17171 | Q10: -89.440857 | S10: 0 | T10: -21.272352 | U10: -2.4330834 | V10: -23.705436 | X10: 0 | Y10: 328.35497 | Z10: 290.91223 | AA10: 619.2672 | AB10: =AA10/G10*100-100 -> -15.448417
A11: Eritrea | B11: i/ | D11: 0 | E11: 0.0 | F11: 0 | G11: 0 | I11: 0 | J11: 0 | K11: 0 | L11: 0 | N11: 0 | O11: 0 | P11: 0 | Q11: 0 | S11: 0 | T11: 0 | U11: 0 | V11: 0 | X11: 0 | Y11: 0 | Z11: 0 | AA11: 0 | AB11: =AA11/G11*100-100 -> #DIV/0!
A12: Eswatini | B12: j/ | D12: 0.0 | E12: 20.795188 | F12: 0 | G12: 20.795188 | I12: 0 | J12: 0 | K12: 0 | L12: 0 | N12: 0 | O12: 0 | P12: 0 | Q12: 0 | S12: 0 | T12: 10.402505 | U12: 0 | V12: 10.402505 | X12: 0 | Y12: 31.197693 | Z12: 0 | AA12: 31.197693 | AB12: =AA12/G12*100-100 -> 50.023617
A13: Ethiopia | B13: h/ | D13: 699.6236 | E13: 469.68986 | F13: 0 | G13: 1169.3135 | I13: 0 | J13: 0 | K13: 0 | L13: 0 | N13: 10.45475 | O13: -15.400314 | P13: 0 | Q13: -4.9455641 | S13: 31.620612 | T13: 0 | U13: 0 | V13: 31.620612 | X13: 741.69896 | Y13: 454.28954 | Z13: 0 | AA13: 1195.9885 | AB13: =AA13/G13*100-100 -> 2.2812572
A14: Kenya | D14: 0.0 | E14: 555.89735 | F14: 143.5878 | G14: 699.48515 | I14: 0 | J14: 0 | K14: 0 | L14: 0 | N14: 0 | O14: -432.55617 | P14: -116.58897 | Q14: -549.14514 | S14: 0 | T14: 78.677635 | U14: 20.322365 | V14: 99 | X14: 0 | Y14: 202.01882 | Z14: 47.321201 | AA14: 249.34002 | AB14: =AA14/G14*100-100 -> -64.35378
A15: Lesotho | B15: g/, b/ | D15: 0.0 | E15: 26.312616 | F15: 6.7965258 | G15: 33.109141 | I15: 0 | J15: 0 | K15: -3.3109141 | L15: -3.3109141 | N15: 0 | O15: -8.9137076 | P15: 1.2821542 | Q15: -7.6315534 | S15: 0 | T15: 0 | U15: 0 | V15: 0 | X15: 0 | Y15: 17.398908 | Z15: 4.7677659 | AA15: 22.166674 | AB15: =AA15/G15*100-100 -> -33.049687
A16: Madagascar | D16: 0.0 | E16: 227.50616 | F16: 26.021639 | G16: 253.5278 | I16: 0 | J16: 0 | K16: 0 | L16: 0 | N16: 0 | O16: -88.456109 | P16: 59.288622 | Q16: -29.167487 | S16: 0 | T16: 13.030071 | U16: 1.4903499 | V16: 14.520421 | X16: 0 | Y16: 152.08013 | Z16: 86.800611 | AA16: 238.88074 | AB16: =AA16/G16*100-100 -> -5.7773018
A17: Malawi | D17: 194.18356 | E17: 0.0 | F17: 0 | G17: 194.18356 | I17: 0 | J17: 0 | K17: 0 | L17: 0 | N17: -179.20473 | O17: 0 | P17: 0 | Q17: -179.20473 | S17: 239.40412 | T17: 0 | U17: 0 | V17: 239.40412 | X17: 254.38294 | Y17: 0 | Z17: 0 | AA17: 254.38294 | AB17: =AA17/G17*100-100 -> 31.001276
A18: Mozambique | B18: f/ | D18: 456.64325 | E18: 0.0 | F18: 0 | G18: 456.64325 | I18: 0 | J18: 0 | K18: 0 | L18: 0 | N18: -68.460515 | O18: -222.5 | P18: 0 | Q18: -290.96052 | S18: 111.6 | T18: 0 | U18: 0 | V18: 111.6 | X18: 499.78273 | Y18: -222.5 | Z18: 0 | AA18: 277.28273 | AB18: =AA18/G18*100-100 -> -39.278039
A19: Rwanda | D19: 0.0 | E19: 234.74258 | F19: 26.849324 | G19: 261.59191 | I19: 0 | J19: 0 | K19: 0 | L19: 0 | N19: 0 | O19: -125.65573 | P19: -15.888758 | Q19: -141.54448 | S19: 0 | T19: 104.48002 | U19: 11.950188 | V19: 116.43021 | X19: 0 | Y19: 213.56688 | Z19: 22.910755 | AA19: 236.47764 | AB19: =AA19/G19*100-100 -> -9.6005543
A20: Sao Tome and Principe | B20: b/ | D20: 16.623402 | E20: 0.0 | F20: 0 | G20: 16.623402 | I20: 4.1647213 | J20: 0 | K20: 0 | L20: 4.1647213 | N20: -8.4882068 | O20: 0 | P20: 0 | Q20: -8.4882068 | S20: 18.2 | T20: 0 | U20: 0 | V20: 18.2 | X20: 30.499917 | Y20: 0 | Z20: 0 | AA20: 30.499917 | AB20: =AA20/G20*100-100 -> 83.47578
A21: Somalia | B21: f/, k/ | D21: 227.73791 | E21: 0.0 | F21: 0 | G21: 227.73791 | I21: 0 | J21: 0 | K21: 0 | L21: 0 | N21: 20.242884 | O21: 0 | P21: 0 | Q21: 20.242884 | S21: -2.3 | T21: 0 | U21: 0 | V21: -2.3 | X21: 245.6808 | Y21: 0 | Z21: 0 | AA21: 245.6808 | AB21: =AA21/G21*100-100 -> 7.8787427
A22: South Sudan | B22: f/ | D22: 71.482788 | E22: 0.0 | F22: 0 | G22: 71.482788 | I22: 0 | J22: 0 | K22: 0 | L22: 0 | N22: 12.008216 | O22: 0 | P22: 0 | Q22: 12.008216 | S22: -2.6 | T22: 0 | U22: 0 | V22: -2.6 | X22: 80.891003 | Y22: 0 | Z22: 0 | AA22: 80.891003 | AB22: =AA22/G22*100-100 -> 13.161512
A23: Sudan | D23: 131.91835 | E23: 0.0 | F23: 0 | G23: 131.91835 | I23: 0 | J23: 0 | K23: 0 | L23: 0 | N23: -3.054738e-13 | O23: 0 | P23: 0 | Q23: -3.054738e-13 | S23: 0 | T23: 0 | U23: 0 | V23: 0 | X23: 131.91835 | Y23: 0 | Z23: 0 | AA23: 131.91835 | AB23: =AA23/G23*100-100 -> -2.2737368e-13
A24: Tanzania | D24: 0.0 | E24: 582.16798 | F24: 66.587054 | G24: 648.75504 | I24: 0 | J24: 0 | K24: 0 | L24: 0 | N24: 0 | O24: -368.85181 | P24: 144.63926 | Q24: -224.21255 | S24: 0 | T24: 124.13 | U24: 14.197708 | V24: 138.3277 | X24: 0 | Y24: 337.44617 | Z24: 225.42403 | AA24: 562.87019 | AB24: =AA24/G24*100-100 -> -13.238409
A25: Uganda | B25: b/ | D25: 0.0 | E25: 485.77218 | F25: 55.561521 | G25: 541.3337 | I25: 0 | J25: 0 | K25: -54.13337 | L25: -54.13337 | N25: 0 | O25: 282.35724 | P25: 19.499822 | Q25: 301.85706 | S25: 0 | T25: -379.87314 | U25: -40.767896 | V25: -420.64103 | X25: 0 | Y25: 388.25629 | Z25: -19.839923 | AA25: 368.41636 | AB25: =AA25/G25*100-100 -> -31.942837
A26: Zambia | D26: 177.33253 | E26: 0.0 | F26: 0 | G26: 177.33253 | I26: 0 | J26: 0 | K26: 0 | L26: 0 | N26: -134.08694 | O26: 0 | P26: 0 | Q26: -134.08694 | S26: 107.74023 | T26: 0 | U26: 0 | V26: 107.74023 | X26: 150.98582 | Y26: 0 | Z26: 0 | AA26: 150.98582 | AB26: =AA26/G26*100-100 -> -14.857234
A27: Zimbabwe | B27: i/ | D27: 0 | E27: 0 | F27: 0 | G27: 0 | I27: 0 | J27: 0 | K27: 0 | L27: 0 | N27: 0 | O27: 0 | P27: 0 | Q27: 0 | S27: 0 | T27: 0 | U27: 0 | V27: 0 | X27: 0 | Y27: 0 | Z27: 0 | AA27: 0 | AB27: =AA27/G27*100-100 -> #DIV/0!
A28: Subtotal | D28: 2176.8426 | E28: 3260.1238 | F28: 400.57747 | G28: 5837.5439 | I28: 4.1647213 | J28: 0 | K28: -57.444285 | L28: -53.279563 | N28: -368.50262 | O28: -1287.5892 | P28: 310.40385 | Q28: -1345.6879 | S28: 584.86774 | T28: -70.425259 | U28: 4.7596313 | V28: 519.20211 | X28: 2397.3724 | Y28: 1902.1094 | Z28: 658.29667 | AA28: 4957.7785 | AB28: =AA28/G28*100-100 -> -15.070814
A29: Africa Western and Central | AB29: =AA29/G29*100-100 -> #DIV/0!
A30: Benin | B30: f/, g/ | D30: 0.0 | E30: 303.46315 | F30: 78.384267 | G30: 381.84741 | I30: 0 | J30: 0 | K30: 0 | L30: 0 | N30: 0 | O30: -30.242666 | P30: 29.354736 | Q30: -0.88792984 | S30: 0 | T30: 0 | U30: 0 | V30: 0 | X30: 0 | Y30: 273.22048 | Z30: 107.739 | AA30: 380.95948 | AB30: =AA30/G30*100-100 -> -0.23253525
A31: Burkina Faso | D31: 0 | E31: 231.44348 | F31: 26.47198 | G31: 257.91546 | I31: 0 | J31: 0 | K31: 0 | L31: 0 | N31: 0 | O31: -5.3582395 | P31: 100.8197 | Q31: 95.46146 | S31: 0 | T31: 0 | U31: 0 | V31: 0 | X31: 0 | Y31: 226.08524 | Z31: 127.29168 | AA31: 353.37692 | AB31: =AA31/G31*100-100 -> 37.012695
A32: Cameroon | D32: 0 | E32: 194.77278 | F32: 50.309641 | G32: 245.08242 | I32: 0 | J32: 0 | K32: 0 | L32: 0 | N32: 0 | O32: -37.547181 | P32: 127.69077 | Q32: 90.143589 | S32: 0 | T32: 0 | U32: 0 | V32: 0 | X32: 0 | Y32: 157.2256 | Z32: 178.00041 | AA32: 335.22601 | AB32: =AA32/G32*100-100 -> 36.780927
A33: Cape Verde | D33: 0.0 | E33: 18.753049 | F33: 4.8438962 | G33: 23.596945 | I33: 0 | J33: 0 | K33: 0 | L33: 0 | N33: 0 | O33: -24.533461 | P33: 6.3260726 | Q33: -18.207388 | S33: 0 | T33: 14.762974 | U33: 2.7080943 | V33: 17.471069 | X33: 0 | Y33: 8.9825619 | Z33: 13.878063 | AA33: 22.860625 | AB33: =AA33/G33*100-100 -> -3.1204027
A34: Central African Republic | D34: 46.322678 | E34: 0 | F34: 0 | G34: 46.322678 | I34: 0 | J34: 0 | K34: 0 | L34: 0 | N34: -18.991229 | O34: 0 | P34: 0 | Q34: -18.991229 | S34: 48.298218 | T34: 0 | U34: 0 | V34: 48.298218 | X34: 75.629667 | Y34: 0 | Z34: 0 | AA34: 75.629667 | AB34: =AA34/G34*100-100 -> 63.267043
A35: Chad | B35: f/ | D35: 157.20933 | E35: 0 | F35: 0 | G35: 157.20933 | I35: 0 | J35: 0 | K35: 0 | L35: 0 | N35: -28.348168 | O35: 0 | P35: 0 | Q35: -28.348168 | S35: 95.110337 | T35: 0 | U35: 0 | V35: 95.110337 | X35: 223.9715 | Y35: 0 | Z35: 0 | AA35: 223.9715 | AB35: =AA35/G35*100-100 -> 42.467054
A36: Congo, Republic of | D36: 0.0 | E36: 40.228183 | F36: 10.390905 | G36: 50.619087 | I36: 0 | J36: 0 | K36: 0 | L36: 0 | N36: 0 | O36: -41.453433 | P36: 1.1007482 | Q36: -40.352685 | S36: 0 | T36: 0 | U36: 0 | V36: 0 | X36: 0 | Y36: -1.2252504 | Z36: 11.491653 | AA36: 10.266402 | AB36: =AA36/G36*100-100 -> -79.718318
A37: Cote d'Ivoire | B37: g/ | D37: 0.0 | E37: 310.30557 | F37: 80.151659 | G37: 390.45723 | I37: 0 | J37: 0 | K37: 0 | L37: 0 | N37: 0 | O37: -144.72877 | P37: -55.071915 | Q37: -199.80068 | S37: 0 | T37: 9.6776624 | U37: 2.4997318 | V37: 12.177394 | X37: 0 | Y37: 175.25446 | Z37: 27.579476 | AA37: 202.83394 | AB37: =AA37/G37*100-100 -> -48.0522
A38: Gambia, The | B38: f/ | D38: 90.424686 | E38: 0.0 | F38: 0 | G38: 90.424686 | I38: 0 | J38: 0 | K38: 0 | L38: 0 | N38: -47.706077 | O38: 0 | P38: 0 | Q38: -47.706077 | S38: 39.381624 | T38: 0 | U38: 0 | V38: 39.381624 | X38: 82.100233 | Y38: 0 | Z38: 0 | AA38: 82.100233 | AB38: =AA38/G38*100-100 -> -9.2059518
A39: Ghana | B39: g/ | D39: 0.0 | E39: 318.74445 | F39: 82.331416 | G39: 401.07587 | I39: 0 | J39: 0 | K39: 0 | L39: 0 | N39: 0 | O39: -54.034087 | P39: -64.379743 | Q39: -118.41383 | S39: 0 | T39: 0 | U39: 0 | V39: 0 | X39: 0 | Y39: 264.71037 | Z39: 17.951673 | AA39: 282.66204 | AB39: =AA39/G39*100-100 -> -29.524047
A40: Guinea | D40: 0.0 | E40: 116.35745 | F40: 13.308701 | G40: 129.66615 | I40: 0 | J40: 0 | K40: 0 | L40: 0 | N40: 0 | O40: 68.684792 | P40: 31.962164 | Q40: 100.64696 | S40: 0 | T40: -10.927528 | U40: -1.2498659 | V40: -12.177394 | X40: 0 | Y40: 174.11471 | Z40: 44.020999 | AA40: 218.13571 | AB40: =AA40/G40*100-100 -> 68.228727
A41: Guinea-Bissau | D41: 23.203898 | E41: 0.0 | F41: 0 | G41: 23.203898 | I41: 0 | J41: 0 | K41: 0 | L41: 0 | N41: 6.1000247 | O41: 0 | P41: 0 | Q41: 6.1000247 | S41: 0 | T41: 0 | U41: 0 | V41: 0 | X41: 29.303923 | Y41: 0 | Z41: 0 | AA41: 29.303923 | AB41: =AA41/G41*100-100 -> 26.288793
A42: Liberia | D42: 0.0 | E42: 47.191048 | F42: 5.3976051 | G42: 52.588654 | I42: 0 | J42: 0 | K42: 0 | L42: 0 | N42: 0 | O42: -14.578313 | P42: 9.7643963 | Q42: -4.8139171 | S42: 0 | T42: 40.007054 | U42: 4.5759161 | V42: 44.582971 | X42: 0 | Y42: 72.619789 | Z42: 19.737918 | AA42: 92.357707 | AB42: =AA42/G42*100-100 -> 75.622878
A43: Mali | D43: 0 | E43: 131.56189 | F43: 15.04775 | G43: 146.60964 | I43: 0 | J43: 0 | K43: 0 | L43: 0 | N43: 0 | O43: 20.947526 | P43: 50.072296 | Q43: 71.019823 | S43: 0 | T43: 33.339212 | U43: 3.8132635 | V43: 37.152475 | X43: 0 | Y43: 185.84863 | Z43: 68.93331 | AA43: 254.78194 | AB43: =AA43/G43*100-100 -> 73.782529
A44: Mauritania | B44: g/ | D44: 0.0 | E44: 53.561268 | F44: 13.834829 | G44: 67.396098 | I44: 0 | J44: 0 | K44: 0 | L44: 0 | N44: 0 | O44: 0.65101816 | P44: -9.8382815 | Q44: -9.1872633 | S44: 0 | T44: 28.93543 | U44: 7.4739964 | V44: 36.409426 | X44: 0 | Y44: 83.147716 | Z44: 11.470544 | AA44: 94.61826 | AB44: =AA44/G44*100-100 -> 40.391304
A45: Niger | D45: 0 | E45: 274.69731 | F45: 31.419255 | G45: 306.11656 | I45: 0 | J45: 0 | K45: 0 | L45: 0 | N45: 0 | O45: 3.471074 | P45: 35.517569 | Q45: 38.988643 | S45: 0 | T45: 0 | U45: 0 | V45: 0 | X45: 0 | Y45: 278.16838 | Z45: 66.936825 | AA45: 345.10521 | AB45: =AA45/G45*100-100 -> 12.736535
A46: Nigeria | D46: 0.0 | E46: 1132.3677 | F46: 292.48958 | G46: 1424.8572 | I46: 0 | J46: 0 | K46: 0 | L46: 0 | N46: 0 | O46: 396.54944 | P46: -67.885754 | Q46: 328.66369 | S46: 0 | T46: 49.013075 | U46: 12.660035 | V46: 61.673109 | X46: 0 | Y46: 1577.9302 | Z46: 237.26387 | AA46: 1815.194 | AB46: =AA46/G46*100-100 -> 27.3948
A47: Senegal | B47: g/ | D47: 0.0 | E47: 192.22581 | F47: 49.651761 | G47: 241.87757 | I47: 0 | J47: 0 | K47: 0 | L47: 0 | N47: 0 | O47: -115.06662 | P47: 60.198239 | Q47: -54.86838 | S47: 0 | T47: 0.87830397 | U47: 0.22686515 | V47: 1.1051691 | X47: 0 | Y47: 78.037497 | Z47: 110.07686 | AA47: 188.11436 | AB47: =AA47/G47*100-100 -> -22.227448
A48: Sierra Leone | D48: 108.97016 | E48: 0.0 | F48: 0 | G48: 108.97016 | I48: 0 | J48: 0 | K48: 0 | L48: 0 | N48: -66.376663 | O48: 0 | P48: 0 | Q48: -66.376663 | S48: 0 | T48: 0 | U48: 0 | V48: 0 | X48: 42.5935 | Y48: 0 | Z48: 0 | AA48: 42.5935 | AB48: =AA48/G48*100-100 -> -60.912695
A49: Togo | B49: f/ | D49: 0.0 | E49: 200.99617 | F49: 22.989486 | G49: 223.98566 | I49: 0 | J49: 0 | K49: 0 | L49: 0 | N49: 0 | O49: -52.936571 | P49: -17.320213 | Q49: -70.256784 | S49: 0 | T49: 0 | U49: 0 | V49: 0 | X49: 0 | Y49: 148.0596 | Z49: 5.6692732 | AA49: 153.72888 | AB49: =AA49/G49*100-100 -> -31.366644
A50: Subtotal | D50: 426.13075 | E50: 3566.6693 | F50: 777.02274 | G50: 4769.8227 | I50: 0 | J50: 0 | K50: 0 | L50: 0 | N50: -155.32211 | O50: -30.175483 | P50: 238.31078 | Q50: 52.813188 | S50: 182.79018 | T50: 165.68618 | U50: 32.708036 | V50: 381.1844 | X50: 453.59882 | Y50: 3702.18 | Z50: 1048.0416 | AA50: 5203.8203 | AB50: =AA50/G50*100-100 -> 9.09882
A51: East Asia and the Pacific | AB51: =AA51/G51*100-100 -> #DIV/0!
A52: Cambodia | B52: g/ | D52: 0.0 | E52: 118.55811 | F52: 30.623457 | G52: 149.18157 | I52: 0 | J52: 0 | K52: 0 | L52: 0 | N52: 0 | O52: -59.847292 | P52: -31.591705 | Q52: -91.438997 | S52: 0 | T52: 0 | U52: 0 | V52: 0 | X52: 0 | Y52: 58.710817 | Z52: -0.96824857 | AA52: 57.742568 | AB52: =AA52/G52*100-100 -> -61.293764
A53: Fiji | D53: 0.0 | E53: 18.125659 | F53: 4.6818419 | G53: 22.8075 | I53: 0 | J53: 0 | K53: 0 | L53: 0 | N53: 0 | O53: -27.032483 | P53: 5.5189211 | Q53: -21.513561 | S53: 0 | T53: 15.890327 | U53: 4.1044577 | V53: 19.994785 | X53: 0 | Y53: 6.9835032 | Z53: 14.305221 | AA53: 21.288724 | AB53: =AA53/G53*100-100 -> -6.6591098
A54: Kiribati | D54: 15.96341 | E54: 0.0 | F54: 0 | G54: 15.96341 | I54: 0 | J54: 0 | K54: 0 | L54: 0 | N54: 21.904744 | O54: 0 | P54: 0 | Q54: 21.904744 | S54: -3.7 | T54: 0 | U54: 0 | V54: -3.7 | X54: 34.168155 | Y54: 0 | Z54: 0 | AA54: 34.168155 | AB54: =AA54/G54*100-100 -> 114.04045
A55: Lao People's Democratic Republic | B55: g/ | D55: 0.0 | E55: 51.018497 | F55: 13.178034 | G55: 64.196531 | I55: 0 | J55: 0 | K55: 0 | L55: 0 | N55: 0 | O55: -0.7978696 | P55: -7.682348 | Q55: -8.4802176 | S55: 0 | T55: 15.594101 | U55: 4.0279427 | V55: 19.622043 | X55: 0 | Y55: 65.814728 | Z55: 9.5236283 | AA55: 75.338357 | AB55: =AA55/G55*100-100 -> 17.355806
A56: Marshall Islands | D56: 15.189267 | E56: 0.0 | F56: 0 | G56: 15.189267 | I56: 0 | J56: 0 | K56: 0 | L56: 0 | N56: 33.586033 | O56: 0 | P56: 0 | Q56: 33.586033 | S56: 7.2 | T56: 0 | U56: 0 | V56: 7.2 | X56: 55.9753 | Y56: 0 | Z56: 0 | AA56: 55.9753 | AB56: =AA56/G56*100-100 -> 268.51878
A57: Micronesia, Federated States of | B57: k/ | D57: 15.650496 | E57: 0.0 | F57: 0 | G57: 15.650496 | I57: 0 | J57: 0 | K57: 0 | L57: 0 | N57: 35.426982 | O57: 0 | P57: 0 | Q57: 35.426982 | S57: 15.527429 | T57: 0 | U57: 0 | V57: 15.527429 | X57: 66.604907 | Y57: 0 | Z57: 0 | AA57: 66.604907 | AB57: =AA57/G57*100-100 -> 325.57698
A58: Myanmar | B58: g/, l/ | D58: 40.802698 | E58: 0 | F58: 0 | G58: 40.802698 | I58: 0 | J58: 0 | K58: 0 | L58: 0 | N58: 21.493171 | O58: 0 | P58: 0 | Q58: 21.493171 | S58: 0 | T58: 0 | U58: 0 | V58: 0 | X58: 62.295869 | Y58: 0 | Z58: 0 | AA58: 62.295869 | AB58: =AA58/G58*100-100 -> 52.675859
A59: Papua New Guinea | B59: b/ | D59: 0.0 | E59: 56.755648 | F59: 14.659935 | G59: 71.415583 | I59: 0 | J59: 0 | K59: 16.306144 | L59: 16.306144 | N59: 0 | O59: 106.24746 | P59: 16.888591 | Q59: 123.13605 | S59: 0 | T59: -3.389852 | U59: -0.75466911 | V59: -4.1445211 | X59: 0 | Y59: 159.61326 | Z59: 47.1 | AA59: 206.71326 | AB59: =AA59/G59*100-100 -> 189.45119
A60: Samoa | D60: 18.384263 | E60: 0.0 | F60: 0 | G60: 18.384263 | I60: 0 | J60: 0 | K60: 0 | L60: 0 | N60: 33.386435 | O60: 0 | P60: 0 | Q60: 33.386435 | S60: -12.282908 | T60: 0 | U60: 0 | V60: -12.282908 | X60: 39.48779 | Y60: 0 | Z60: 0 | AA60: 39.48779 | AB60: =AA60/G60*100-100 -> 114.79126
A61: Solomon Islands | D61: 9.6730038 | E61: 7.6873643 | F61: 1.9856395 | G61: 19.346008 | I61: 0 | J61: 0 | K61: 0 | L61: 0 | N61: -1.7947924 | O61: 6.2830308 | P61: 5.0181085 | Q61: 9.5063469 | S61: 9.555333 | T61: 7.5938485 | U61: 1.9614845 | V61: 19.110666 | X61: 17.433544 | Y61: 21.564244 | Z61: 8.9652326 | AA61: 47.963021 | AB61: =AA61/G61*100-100 -> 147.92206
A62: Timor-Leste | B62: b/ | D62: 0.0 | E62: 17.17182 | F62: 4.4354661 | G62: 21.607286 | I62: 0 | J62: 0 | K62: -2.1607286 | L62: -2.1607286 | N62: 0 | O62: -11.891714 | P62: 5.2202914 | Q62: -6.6714229 | S62: 0 | T62: -10.152701 | U62: -2.6224338 | V62: -12.775134 | X62: 0 | Y62: -4.8725952 | Z62: 4.8725952 | AA62: 6.9277917e-14 | AB62: =AA62/G62*100-100 -> -100
A63: Tonga | B63: b/ | D63: 16.046155 | E63: 0.0 | F63: 0 | G63: 16.046155 | I63: 4.0341613 | J63: 0 | K63: 0 | L63: 4.0341613 | N63: 24.567382 | O63: 0 | P63: 0 | Q63: 24.567382 | S63: 0 | T63: 0 | U63: 0 | V63: 0 | X63: 44.647699 | Y63: 0 | Z63: 0 | AA63: 44.647699 | AB63: =AA63/G63*100-100 -> 178.24547
A64: Tuvalu | D64: 15.073557 | E64: 0.0 | F64: 0 | G64: 15.073557 | I64: 0 | J64: 0 | K64: 0 | L64: 0 | N64: -12.891375 | O64: 0 | P64: 0 | Q64: -12.891375 | S64: 0 | T64: 0 | U64: 0 | V64: 0 | X64: 2.1821816 | Y64: 0 | Z64: 0 | AA64: 2.1821816 | AB64: =AA64/G64*100-100 -> -85.523114
A65: Vanuatu | B65: l/ | D65: 8.8777948 | E65: 7.0553929 | F65: 1.8224019 | G65: 17.75559 | I65: 0 | J65: 0 | K65: 0 | L65: 0 | N65: -3.0656679 | O65: -6.6197894 | P65: -0.045878428 | Q65: -9.7313357 | S65: 9.5630888 | T65: 1.4305025 | U65: 0.36949754 | V65: 11.363089 | X65: 15.375216 | Y65: 1.8661059 | Z65: 2.146021 | AA65: 19.387343 | AB65: =AA65/G65*100-100 -> 9.190081
A66: Subtotal | D66: 155.66064 | E66: 276.37249 | F66: 71.386774 | G66: 503.41991 | I66: 4.0341613 | J66: 0 | K66: 14.145415 | L66: 18.179576 | N66: 152.61291 | O66: 6.3413432 | P66: -6.6740197 | Q66: 152.28024 | S66: 25.862943 | T66: 26.966226 | U66: 7.0862796 | V66: 59.915449 | X66: 338.17066 | Y66: 309.68006 | Z66: 85.944449 | AA66: 733.79517 | AB66: =AA66/G66*100-100 -> 45.762048
A67: Europe and Central Asia | AB67: =AA67/G67*100-100 -> #DIV/0!
A68: Kosovo | B68: g/ | D68: 0.0 | E68: 26.793579 | F68: 6.9207582 | G68: 33.714337 | I68: 0 | J68: 0 | K68: 0 | L68: 0 | N68: 0 | O68: 7.4414792 | P68: 5.3361501 | Q68: 12.777629 | S68: 0 | T68: 0 | U68: 0 | V68: 0 | X68: 0 | Y68: 34.235058 | Z68: 12.256908 | AA68: 46.491966 | AB68: =AA68/G68*100-100 -> 37.89969
A69: Kyrgyz Republic | D69: 0.0 | E69: 70.591719 | F69: 8.0741208 | G69: 78.66584 | I69: 0 | J69: 0 | K69: 0 | L69: 0 | N69: 0 | O69: -25.111936 | P69: -1.2251703 | Q69: -26.337106 | S69: 0 | T69: 123.58334 | U69: 14.135182 | V69: 137.71852 | X69: 0 | Y69: 169.06312 | Z69: 20.984133 | AA69: 190.04726 | AB69: =AA69/G69*100-100 -> 141.58803
A70: Tajikistan | D70: 99.262628 | E70: 0.0 | F70: 0 | G70: 99.262628 | I70: 0 | J70: 0 | K70: 0 | L70: 0 | N70: 133.76654 | O70: 0 | P70: 0 | Q70: 133.76654 | S70: -36.283996 | T70: 0 | U70: 0 | V70: -36.283996 | X70: 196.74517 | Y70: 0 | Z70: 0 | AA70: 196.74517 | AB70: =AA70/G70*100-100 -> 98.206688
A71: Uzbekistan | D71: 0.0 | E71: 385.09772 | F71: 99.470408 | G71: 484.56813 | I71: 0 | J71: 0 | K71: 0 | L71: 0 | N71: 0 | O71: 136.24074 | P71: 4.4698025 | Q71: 140.71055 | S71: 0 | T71: -58.934493 | U71: 0 | V71: -58.934493 | X71: 0 | Y71: 462.40397 | Z71: 103.94021 | AA71: 566.34418 | AB71: =AA71/G71*100-100 -> 16.876069
A72: Subtotal | D72: 99.262628 | E72: 482.48302 | F72: 114.46529 | G72: 696.21094 | I72: 0 | J72: 0 | K72: 0 | L72: 0 | N72: 133.76654 | O72: 118.57029 | P72: 8.5807823 | Q72: 260.9176 | S72: -36.283996 | T72: 64.648847 | U72: 14.135182 | V72: 42.500033 | X72: 196.74517 | Y72: 665.70215 | Z72: 137.18125 | AA72: 999.62857 | AB72: =AA72/G72*100-100 -> 43.58128
A73: Latin America and the Caribbean | AB73: =AA73/G73*100-100 -> #DIV/0!
A74: Belize | B74: j/ | D74: 0.0 | E74: 13.917659 | F74: 3.5949193 | G74: 17.512578 | I74: 0 | J74: 0 | K74: 0 | L74: 0 | N74: 0 | O74: 0 | P74: 0 | Q74: 0 | S74: 0 | T74: 0 | U74: 0 | V74: 0 | X74: 0 | Y74: 13.917659 | Z74: 3.5949193 | AA74: 17.512578 | AB74: =AA74/G74*100-100 -> 0
A75: Dominica | D75: 0.0 | E75: 15.783923 | F75: 0 | G75: 15.783923 | I75: 0 | J75: 0 | K75: 0 | L75: 0 | N75: 0 | O75: 20.362383 | P75: 0 | Q75: 20.362383 | S75: 0 | T75: 3.41 | U75: 0 | V75: 3.41 | X75: 0 | Y75: 39.556306 | Z75: 0 | AA75: 39.556306 | AB75: =AA75/G75*100-100 -> 150.61137
A76: Grenada | D76: 0.0 | E76: 16.236096 | F76: 0 | G76: 16.236096 | I76: 0 | J76: 0 | K76: 0 | L76: 0 | N76: 0 | O76: 10.269656 | P76: 0 | Q76: 10.269656 | S76: 0 | T76: 0 | U76: 0 | V76: 0 | X76: 0 | Y76: 26.505751 | Z76: 0 | AA76: 26.505751 | AB76: =AA76/G76*100-100 -> 63.252002
A77: Guyana | B77: g/ | D77: 0.0 | E77: 16.289638 | F77: 4.2075994 | G77: 20.497238 | I77: 0 | J77: 0 | K77: 0 | L77: 0 | N77: 0 | O77: 51.66057 | P77: 16.142555 | Q77: 67.803124 | S77: 0 | T77: 0 | U77: 0 | V77: 0 | X77: 0 | Y77: 67.950208 | Z77: 20.350154 | AA77: 88.300362 | AB77: =AA77/G77*100-100 -> 330.79152
A78: Haiti | B78: f/, g/, k/ | D78: 63.873749 | E78: 0 | F78: 0 | G78: 63.873749 | I78: 0 | J78: 0 | K78: 0 | L78: 0 | N78: -8.9924292 | O78: 0 | P78: 0 | Q78: -8.9924292 | S78: 53.844674 | T78: 0 | U78: 0 | V78: 53.844674 | X78: 108.72599 | Y78: 0 | Z78: 0 | AA78: 108.72599 | AB78: =AA78/G78*100-100 -> 70.220154
A79: Honduras | B79: g/ | D79: 0.0 | E79: 64.958899 | F79: 16.778827 | G79: 81.737727 | I79: 0 | J79: 0 | K79: 0 | L79: 0 | N79: 0 | O79: 118.73116 | P79: 46.443082 | Q79: 165.17424 | S79: 0 | T79: 1.4253644 | U79: 0.36817038 | V79: 1.7935348 | X79: 0 | Y79: 185.11542 | Z79: 63.590079 | AA79: 248.7055 | AB79: =AA79/G79*100-100 -> 204.27259
A80: Nicaragua | B80: b/, g/ | D80: 0.0 | E80: 44.743574 | F80: 11.557226 | G80: 56.300801 | I80: 0 | J80: 0 | K80: -5.6300801 | L80: -5.6300801 | N80: 0 | O80: -43.364994 | P80: -7.8636579 | Q80: -51.228652 | S80: 0 | T80: 0 | U80: 0 | V80: 0 | X80: 0 | Y80: 1.3785804 | Z80: -1.9365115 | AA80: -0.55793118 | AB80: =AA80/G80*100-100 -> -100.99098
A81: St. Lucia | D81: 0.0 | E81: 17.112466 | F81: 0 | G81: 17.112466 | I81: 0 | J81: 0 | K81: 0 | L81: 0 | N81: 0 | O81: 3.714733 | P81: 0 | Q81: 3.714733 | S81: 0 | T81: 2.5718448 | U81: 0 | V81: 2.5718448 | X81: 0 | Y81: 23.399044 | Z81: 0 | AA81: 23.399044 | AB81: =AA81/G81*100-100 -> 36.736832
A82: St. Vincent and the Grenadines | D82: 0.0 | E82: 16.134927 | F82: 0 | G82: 16.134927 | I82: 0 | J82: 0 | K82: 0 | L82: 0 | N82: 0 | O82: 22.421492 | P82: 0 | Q82: 22.421492 | S82: 0 | T82: -14.527583 | U82: 0 | V82: -14.527583 | X82: 0 | Y82: 24.028836 | Z82: 0 | AA82: 24.028836 | AB82: =AA82/G82*100-100 -> 48.924356
A83: Suriname | B83: j/ | D83: 0 | E83: 16.99659 | F83: 0 | G83: 16.99659 | I83: 0 | J83: 0 | K83: 0 | L83: 0 | N83: 0 | O83: 0 | P83: 0 | Q83: 0 | S83: 0 | T83: 0 | U83: 0 | V83: 0 | X83: 0 | Y83: 16.99659 | Z83: 0 | AA83: 16.99659 | AB83: =AA83/G83*100-100 -> 0
A84: Subtotal | D84: 63.873749 | E84: 222.17377 | F84: 36.138573 | G84: 322.18609 | I84: 0 | J84: 0 | K84: -5.6300801 | L84: -5.6300801 | N84: -8.9924292 | O84: 183.795 | P84: 54.721978 | Q84: 229.52455 | S84: 53.844674 | T84: -7.1203739 | U84: 0.36817038 | V84: 47.092471 | X84: 108.72599 | Y84: 398.8484 | Z84: 85.598641 | AA84: 593.17303 | AB84: =AA84/G84*100-100 -> 84.108825
A85: Middle East and North Africa | AB85: =AA85/G85*100-100 -> #DIV/0!
A86: Djibouti | B86: b/ | D86: 23.95007 | E86: 0.0 | F86: 0 | G86: 23.95007 | I86: -4.790014 | J86: 0 | K86: 0 | L86: -4.790014 | N86: 26.800753 | O86: 0 | P86: 0 | Q86: 26.800753 | S86: -0.19133944 | T86: 0 | U86: 0 | V86: -0.19133944 | X86: 45.769469 | Y86: 0 | Z86: 0 | AA86: 45.769469 | AB86: =AA86/G86*100-100 -> 91.103699
A87: Syria | B87: i/ | D87: 107.7 | E87: 0 | F87: 0 | G87: 107.7 | I87: 0 | J87: 0 | K87: 0 | L87: 0 | N87: 0 | O87: 0 | P87: 0 | Q87: 0 | S87: 0 | T87: 0 | U87: 0 | V87: 0 | X87: 107.7 | Y87: 0 | Z87: 0 | AA87: 107.7 | AB87: =AA87/G87*100-100 -> 0
A88: Yemen, Republic of | B88: f/ | D88: 130.50878 | E88: 0.0 | F88: 0 | G88: 130.50878 | I88: 0 | J88: 0 | K88: 0 | L88: 0 | N88: -100.64613 | O88: 0 | P88: 0 | Q88: -100.64613 | S88: 61.602629 | T88: 0 | U88: 0 | V88: 61.602629 | X88: 91.465271 | Y88: 0 | Z88: 0 | AA88: 91.465271 | AB88: =AA88/G88*100-100 -> -29.916383
A89: Subtotal | D89: 262.15885 | E89: 0 | F89: 0 | G89: 262.15885 | I89: -4.790014 | J89: 0 | K89: 0 | L89: -4.790014 | N89: -73.845381 | O89: 0 | P89: 0 | Q89: -73.845381 | S89: 61.411289 | T89: 0 | U89: 0 | V89: 61.411289 | X89: 244.93474 | Y89: 0 | Z89: 0 | AA89: 244.93474 | AB89: =AA89/G89*100-100 -> -6.5701029
A90: South Asia | AB90: =AA90/G90*100-100 -> #DIV/0!
A91: Afghanistan | D91: 80.863329 | E91: 0.0 | F91: 0 | G91: 80.863329 | I91: 0 | J91: 0 | K91: 0 | L91: 0 | N91: 102.11315 | O91: 0 | P91: 0 | Q91: 102.11315 | S91: 3.3 | T91: 0 | U91: 0 | V91: 3.3 | X91: 186.27647 | Y91: 0 | Z91: 0 | AA91: 186.27647 | AB91: =AA91/G91*100-100 -> 130.35964
A92: Bangladesh | B92: g/ | D92: 0.0 | E92: 850.06233 | F92: 219.57036 | G92: 1069.6327 | I92: 0 | J92: 0 | K92: 0 | L92: 0 | N92: 0 | O92: -547.9501 | P92: 70.660683 | Q92: -477.28941 | S92: 0 | T92: 0 | U92: 0 | V92: 0 | X92: 0 | Y92: 302.11224 | Z92: 290.23105 | AA92: 592.34328 | AB92: =AA92/G92*100-100 -> -44.621805
A93: Bhutan | D93: 13.083015 | E93: 10.397381 | F93: 2.6856345 | G93: 26.166031 | I93: 0 | J93: 0 | K93: 0 | L93: 0 | N93: 0 | O93: 15.190261 | P93: 4.6120501 | Q93: 19.802311 | S93: 11.4 | T93: 9.0598489 | U93: 2.3401511 | V93: 22.8 | X93: 24.483015 | Y93: 34.647491 | Z93: 9.6378357 | AA93: 68.768342 | AB93: =AA93/G93*100-100 -> 162.81534
A94: Maldives | B94: b/ | D94: 0 | E94: 18.464287 | F94: 0 | G94: 18.464287 | I94: 0 | J94: 0 | K94: 0 | L94: 0 | N94: -3.5093754 | O94: 18.735743 | P94: 0 | Q94: 15.226368 | S94: 0 | T94: -33.690655 | U94: 0 | V94: -33.690655 | X94: -3.5093754 | Y94: 3.5093754 | Z94: 0 | AA94: -7.8159701e-14 | AB94: =AA94/G94*100-100 -> -100
A95: Nepal | D95: 0.0 | E95: 193.66561 | F95: 50.02366 | G95: 243.68927 | I95: 0 | J95: 0 | K95: 0 | L95: 0 | N95: 0 | O95: 85.692149 | P95: 13.241997 | Q95: 98.934146 | S95: 0 | T95: 10.006091 | U95: 2.5845645 | V95: 12.590655 | X95: 0 | Y95: 289.36385 | Z95: 65.850222 | AA95: 355.21408 | AB95: =AA95/G95*100-100 -> 45.765166
A96: Pakistan | D96: 0.0 | E96: 814.77172 | F96: 210.45483 | G96: 1025.2265 | I96: 0 | J96: 0 | K96: 0 | L96: 0 | N96: 0 | O96: 102.43979 | P96: -233.66181 | Q96: -131.22202 | S96: 0 | T96: 0 | U96: 0 | V96: 0 | X96: 0 | Y96: 917.21152 | Z96: -23.20698 | AA96: 894.00453 | AB96: =AA96/G96*100-100 -> -12.799319
A97: Sri Lanka | B97: g/ | D97: 0.0 | E97: 160.0417 | F97: 41.338632 | G97: 201.38033 | I97: 0 | J97: 0 | K97: 0 | L97: 0 | N97: 0 | O97: 66.195125 | P97: 8.0049437 | Q97: 74.200068 | S97: 0 | T97: -3.9736179 | U97: -1.0263821 | V97: -5 | X97: 0 | Y97: 222.2632 | Z97: 48.317193 | AA97: 270.5804 | AB97: =AA97/G97*100-100 -> 34.362874
A98: Subtotal | D98: 93.946345 | E98: 2047.403 | F98: 524.07312 | G98: 2665.4225 | I98: 0 | J98: 0 | K98: 0 | L98: 0 | N98: 98.60377 | O98: -259.69702 | P98: -137.14214 | Q98: -298.23539 | S98: 14.7 | T98: -18.598334 | U98: 3.8983336 | V98: 0 | X98: 207.25011 | Y98: 1769.1077 | Z98: 390.82932 | AA98: 2367.1871 | AB98: =AA98/G98*100-100 -> -11.189048
A99: Total Regions | D99: 3277.8755 | E99: 9855.2254 | F99: 1923.664 | G99: 15056.765 | I99: 3.4088687 | J99: 0 | K99: -48.92895 | L99: -45.520081 | N99: -221.67933 | O99: -1268.755 | P99: 468.20124 | Q99: -1022.2331 | S99: 887.19283 | T99: 161.15729 | U99: 62.955633 | V99: 1111.3057 | X99: 3946.7979 | Y99: 8747.6276 | Z99: 2405.8919 | AA99: 15100.317 | AB99: =AA99/G99*100-100 -> 0.2892556
G100: =10000/G99 -> 0.66415329
A101: a/ Reflects FY25 country allocations before FY25 set-aside adjustment, FY24 front-/back-loading adjustment, and FY25 reallocations. Also, total amounts include Myanmar's reduced amount of country allocation as well as adjusted financing terms for select countries (see footnotes "k" and "l").
...

Sheet Sheet1

Sheet Table 2
B1: Table 2. Key Input Data for FY25 Allocations | F1: =CORREL(F7:F90,$O$7:$O$90) -> 0.11830706 | G1: =CORREL(G7:G90,$O$7:$O$90) -> 0.90809968 | H1: =CORREL(H7:H90,$O$7:$O$90) -> -0.28543817
B3: Country | C3: 2023
C4: Average of CPIA Clusters A, B & C | D4: CPIA Cluster D | E4: Portfolio Performance Rating (PPR) | F4: Country Performance Rating (CPR) | G4: Population (million) | H4: GNI per Capita (US$)
B6: Africa Eastern and Southern
A7: BJ | B7: Burundi | C7: 3.2888887 | D7: 2.4 | E7: 3.5 | F7: 2.7013333 | G7: 13.238559 | H7: 230 | J7: =(F7^3)*(H7^-0.125)*G7 -> 132.2389 | L7: =IF(ISERROR(J7),"",J7/N7) -> 0.78644336 | N7: =O7-15 -> 168.14803 | O7: =VLOOKUP(B7,'Table 1'!$A$8:$G$99,7,FALSE) -> 183.14803
A8: BF | B8: Comoros | C8: 2.8555557 | D8: 2.1 | E8: 3.5 | F8: 2.3933334 | G8: 0.852075 | H8: 1600 | J8: =(F8^3)*(H8^-0.125)*G8 -> 4.6448576 | L8: =IF(ISERROR(J8),"",J8/N8) -> 1.4749585 | N8: =O8-15 -> 3.1491447 | O8: =VLOOKUP(B8,'Table 1'!$A$8:$G$99,7,FALSE) -> 18.149145
A9: BI | B9: Congo, Democratic Republic of | C9: 3.3666667 | D9: 2.6 | E9: 3.5 | F9: 2.856 | G9: 102.26281 | H9: 660 | J9: =(F9^3)*(H9^-0.125)*G9 -> 1058.1551 | L9: =IF(ISERROR(J9),"",J9/N9) -> 1.4749585 | N9: =O9-15 -> 717.41349 | O9: =VLOOKUP(B9,'Table 1'!$A$8:$G$99,7,FALSE) -> 732.41349
A10: CM | B10: Eritrea | C10: 1.7555557 | D10: 1.5 | E10: na | F10: 1.5817778 | G10: 3.748901 | H10: na | J10: =(F10^3)*(H10^-0.125)*G10 -> #VALUE! | L10: =IF(ISERROR(J10),"",J10/N10) | N10: =O10-15 -> -15 | O10: =VLOOKUP(B10,'Table 1'!$A$8:$G$99,7,FALSE) -> 0
B11: Eswatini | C11: na | D11: na | E11: na | F11: na | G11: 1.210822 | H11: 3860 | J11: =(F11^3)*(H11^-0.125)*G11 -> #VALUE! | L11: =IF(ISERROR(J11),"",J11/N11) | N11: =O11-15 -> 5.7951876 | O11: =VLOOKUP(B11,'Table 1'!$A$8:$G$99,7,FALSE) -> 20.795188
A12: CV | B12: Ethiopia | C12: 3.1666667 | D12: 3.1 | E12: 4 | F12: 3.188 | G12: 126.52706 | H12: 1130 | J12: =(F12^3)*(H12^-0.125)*G12 -> 1702.5644 | L12: =IF(ISERROR(J12),"",J12/N12) -> 1.4749585 | N12: =O12-15 -> 1154.3135 | O12: =VLOOKUP(B12,'Table 1'!$A$8:$G$99,7,FALSE) -> 1169.3135
A13: CF | B13: Kenya | C13: 3.911111 | D13: 3.6 | E13: 3 | F13: 3.6266666 | G13: 55.100586 | H13: 2110 | J13: =(F13^3)*(H13^-0.125)*G13 -> 1009.5872 | L13: =IF(ISERROR(J13),"",J13/N13) -> 1.4749585 | N13: =O13-15 -> 684.48515 | O13: =VLOOKUP(B13,'Table 1'!$A$8:$G$99,7,FALSE) -> 699.48515
A14: TD | B14: Lesotho | C14: 3.388889 | D14: 2.9 | E14: 3 | F14: 3.0253334 | G14: 2.330318 | H14: 1160 | J14: =(F14^3)*(H14^-0.125)*G14 -> 26.710231 | L14: =IF(ISERROR(J14),"",J14/N14) -> 1.4749585 | N14: =O14-15 -> 18.109141 | O14: =VLOOKUP(B14,'Table 1'!$A$8:$G$99,7,FALSE) -> 33.109141
A15: KM | B15: Madagascar | C15: 3.4333333 | D15: 2.7 | E15: 3.5 | F15: 2.94 | G15: 30.325732 | H15: 530 | J15: =(F15^3)*(H15^-0.125)*G15 -> 351.8186 | L15: =IF(ISERROR(J15),"",J15/N15) -> 1.4749585 | N15: =O15-15 -> 238.5278 | O15: =VLOOKUP(B15,'Table 1'!$A$8:$G$99,7,FALSE) -> 253.5278
A16: ZR | B16: Malawi | C16: 3.0333333 | D16: 3 | E16: 3.5 | F16: 3.048 | G16: 20.931751 | H16: 640 | J16: =(F16^3)*(H16^-0.125)*G16 -> 264.28831 | L16: =IF(ISERROR(J16),"",J16/N16) -> 1.4749585 | N16: =O16-15 -> 179.18356 | O16: =VLOOKUP(B16,'Table 1'!$A$8:$G$99,7,FALSE) -> 194.18356
A17: CG | B17: Mozambique | C17: 3.2111113 | D17: 2.9 | E17: 3 | F17: 2.9826667 | G17: 33.897354 | H17: 530 | J17: =(F17^3)*(H17^-0.125)*G17 -> 410.62511 | L17: =IF(ISERROR(J17),"",J17/N17) -> 0.92976652 | N17: =O17-15 -> 441.64325 | O17: =VLOOKUP(B17,'Table 1'!$A$8:$G$99,7,FALSE) -> 456.64325
A18: CI | B18: Rwanda | C18: 4.188889 | D18: 3.9 | E18: 3.5 | F18: 3.9373334 | G18: 14.094683 | H18: 980 | J18: =(F18^3)*(H18^-0.125)*G18 -> 363.71282 | L18: =IF(ISERROR(J18),"",J18/N18) -> 1.4749585 | N18: =O18-15 -> 246.59191 | O18: =VLOOKUP(B18,'Table 1'!$A$8:$G$99,7,FALSE) -> 261.59191
A19: ER | B19: Sao Tome and Principe | C19: 2.9 | D19: 3 | E19: 3.5 | F19: 3.016 | G19: 0.231856 | H19: 2480 | J19: =(F19^3)*(H19^-0.125)*G19 -> 2.3944507 | L19: =IF(ISERROR(J19),"",J19/N19) -> 1.4749585 | N19: =O19-15 -> 1.6234021 | O19: =VLOOKUP(B19,'Table 1'!$A$8:$G$99,7,FALSE) -> 16.623402
A20: ET | B20: Somalia | C20: 2.3333333 | D20: 1.9 | E20: 4 | F20: 2.172 | G20: 18.143378 | H20: 610 | J20: =(F20^3)*(H20^-0.125)*G20 -> 83.393343 | L20: =IF(ISERROR(J20),"",J20/N20) -> 0.39200038 | N20: =O20-15 -> 212.73791 | O20: =VLOOKUP(B20,'Table 1'!$A$8:$G$99,7,FALSE) -> 227.73791
A21: GM | B21: South Sudan | C21: 1.788889 | D21: 1.3 | E21: 3.5 | F21: 1.5933334 | G21: 11.088796 | H21: na | J21: =(F21^3)*(H21^-0.125)*G21 -> #VALUE! | L21: =IF(ISERROR(J21),"",J21/N21) | N21: =O21-15 -> 56.482788 | O21: =VLOOKUP(B21,'Table 1'!$A$8:$G$99,7,FALSE) -> 71.482788
A22: GH | B22: Sudan | C22: 2.0666667 | D22: 1.8 | E22: 4 | F22: 2.04 | G22: 48.109006 | H22: 990 | J22: =(F22^3)*(H22^-0.125)*G22 -> 172.44972 | L22: =IF(ISERROR(J22),"",J22/N22) -> 1.4749585 | N22: =O22-15 -> 116.91835 | O22: =VLOOKUP(B22,'Table 1'!$A$8:$G$99,7,FALSE) -> 131.91835
A23: GN | B23: Tanzania | C23: 3.6444447 | D23: 3.1 | E23: 3.5 | F23: 3.2626667 | G23: 65.36289 | H23: 1210 | J23: =(F23^3)*(H23^-0.125)*G23 -> 934.76235 | L23: =IF(ISERROR(J23),"",J23/N23) -> 1.4749585 | N23: =O23-15 -> 633.75504 | O23: =VLOOKUP(B23,'Table 1'!$A$8:$G$99,7,FALSE) -> 648.75504
A24: GW | B24: Uganda | C24: 3.6333333 | D24: 3.3 | E24: 3 | F24: 3.356 | G24: 48.582334 | H24: 980 | J24: =(F24^3)*(H24^-0.125)*G24 -> 776.32035 | L24: =IF(ISERROR(J24),"",J24/N24) -> 1.4749585 | N24: =O24-15 -> 526.3337 | O24: =VLOOKUP(B24,'Table 1'!$A$8:$G$99,7,FALSE) -> 541.3337
A25: KE | B25: Zambia | C25: 3.3555553 | D25: 2.9 | E25: 3.5 | F25: 3.0573333 | G25: 20.569737 | H25: 1320 | J25: =(F25^3)*(H25^-0.125)*G25 -> 239.43374 | L25: =IF(ISERROR(J25),"",J25/N25) -> 1.4749585 | N25: =O25-15 -> 162.33253 | O25: =VLOOKUP(B25,'Table 1'!$A$8:$G$99,7,FALSE) -> 177.33253
A26: LS | B26: Zimbabwe | C26: 3.011111 | D26: 2.9 | E26: 4.5 | F26: 3.0546666 | G26: 16.665409 | H26: 1740 | J26: =(F26^3)*(H26^-0.125)*G26 -> 186.91269 | L26: =IF(ISERROR(J26),"",J26/N26) -> -12.460846 | N26: =O26-15 -> -15 | O26: =VLOOKUP(B26,'Table 1'!$A$8:$G$99,7,FALSE) -> 0
B27: Africa Western and Central | J27: =(F27^3)*(H27^-0.125)*G27 -> #DIV/0! | L27: =IF(ISERROR(J27),"",J27/N27) | N27: =O27-15 -> -15 | O27: =VLOOKUP(B27,'Table 1'!$A$8:$G$99,7,FALSE) -> 0
A28: LR | B28: Benin | C28: 3.9666667 | D28: 3.7 | E28: 4 | F28: 3.788 | G28: 13.712828 | H28: 1440 | J28: =(F28^3)*(H28^-0.125)*G28 -> 300.30435 | L28: =IF(ISERROR(J28),"",J28/N28) -> 0.81860835 | N28: =O28-15 -> 366.84741 | O28: =VLOOKUP(B28,'Table 1'!$A$8:$G$99,7,FALSE) -> 381.84741
A29: MG | B29: Burkina Faso | C29: 3.5 | D29: 3.2 | E29: 3.5 | F29: 3.296 | G29: 23.251485 | H29: 850 | J29: =(F29^3)*(H29^-0.125)*G29 -> 358.29021 | L29: =IF(ISERROR(J29),"",J29/N29) -> 1.4749585 | N29: =O29-15 -> 242.91546 | O29: =VLOOKUP(B29,'Table 1'!$A$8:$G$99,7,FALSE) -> 257.91546
A30: MW | B30: Cameroon | C30: 3.4333333 | D30: 3 | E30: 3 | F30: 3.104 | G30: 28.647293 | H30: 1650 | J30: =(F30^3)*(H30^-0.125)*G30 -> 339.36202 | L30: =IF(ISERROR(J30),"",J30/N30) -> 1.4749585 | N30: =O30-15 -> 230.08242 | O30: =VLOOKUP(B30,'Table 1'!$A$8:$G$99,7,FALSE) -> 245.08242
A31: ML | B31: Cape Verde | C31: 3.8333333 | D31: 4 | E31: 3.5 | F31: 3.92 | G31: 0.598682 | H31: 4280 | J31: =(F31^3)*(H31^-0.125)*G31 -> 12.680137 | L31: =IF(ISERROR(J31),"",J31/N31) -> 1.4749585 | N31: =O31-15 -> 8.5969448 | O31: =VLOOKUP(B31,'Table 1'!$A$8:$G$99,7,FALSE) -> 23.596945
A32: MR | B32: Central African Republic | C32: 2.6555557 | D32: 2.4 | E32: 4 | F32: 2.5893334 | G32: 5.742315 | H32: 470 | J32: =(F32^3)*(H32^-0.125)*G32 -> 46.199649 | L32: =IF(ISERROR(J32),"",J32/N32) -> 1.4749585 | N32: =O32-15 -> 31.322678 | O32: =VLOOKUP(B32,'Table 1'!$A$8:$G$99,7,FALSE) -> 46.322678
A33: MZ | B33: Chad | C33: 2.8 | D33: 2.4 | E33: 3 | F33: 2.544 | G33: 18.278568 | H33: 710 | J33: =(F33^3)*(H33^-0.125)*G33 -> 132.46044 | L33: =IF(ISERROR(J33),"",J33/N33) -> 0.93144693 | N33: =O33-15 -> 142.20933 | O33: =VLOOKUP(B33,'Table 1'!$A$8:$G$99,7,FALSE) -> 157.20933
A34: NE | B34: Congo, Republic of | C34: 2.888889 | D34: 2.8 | E34: 3 | F34: 2.8373334 | G34: 6.106869 | H34: 2470 | J34: =(F34^3)*(H34^-0.125)*G34 -> 52.536674 | L34: =IF(ISERROR(J34),"",J34/N34) -> 1.4749585 | N34: =O34-15 -> 35.619087 | O34: =VLOOKUP(B34,'Table 1'!$A$8:$G$99,7,FALSE) -> 50.619087
A35: NG | B35: Cote d'Ivoire | C35: 3.8444443 | D35: 3.7 | E35: 3.5 | F35: 3.7186666 | G35: 28.873034 | H35: 2670 | J35: =(F35^3)*(H35^-0.125)*G35 -> 553.78381 | L35: =IF(ISERROR(J35),"",J35/N35) -> 1.4749585 | N35: =O35-15 -> 375.45723 | O35: =VLOOKUP(B35,'Table 1'!$A$8:$G$99,7,FALSE) -> 390.45723
A36: RW | B36: Gambia, The | C36: 3.1444447 | D36: 3.1 | E36: 3.5 | F36: 3.1426667 | G36: 2.773168 | H36: 830 | J36: =(F36^3)*(H36^-0.125)*G36 -> 37.152359 | L36: =IF(ISERROR(J36),"",J36/N36) -> 0.49257559 | N36: =O36-15 -> 75.424686 | O36: =VLOOKUP(B36,'Table 1'!$A$8:$G$99,7,FALSE) -> 90.424686
A37: ST | B37: Ghana | C37: 3.3444443 | D37: 3.6 | E37: 3.5 | F37: 3.5306666 | G37: 34.121985 | H37: 2340 | J37: =(F37^3)*(H37^-0.125)*G37 -> 569.44587 | L37: =IF(ISERROR(J37),"",J37/N37) -> 1.4749585 | N37: =O37-15 -> 386.07587 | O37: =VLOOKUP(B37,'Table 1'!$A$8:$G$99,7,FALSE) -> 401.07587
A38: SN | B38: Guinea | C38: 3.522222 | D38: 3 | E38: 2.5 | F38: 3.0853333 | G38: 14.190612 | H38: 1360 | J38: =(F38^3)*(H38^-0.125)*G38 -> 169.12781 | L38: =IF(ISERROR(J38),"",J38/N38) -> 1.4749585 | N38: =O38-15 -> 114.66615 | O38: =VLOOKUP(B38,'Table 1'!$A$8:$G$99,7,FALSE) -> 129.66615
A39: SL | B39: Guinea-Bissau | C39: 2.722222 | D39: 2.1 | E39: 3.5 | F39: 2.3613333 | G39: 2.150842 | H39: 900 | J39: =(F39^3)*(H39^-0.125)*G39 -> 12.100409 | L39: =IF(ISERROR(J39),"",J39/N39) -> 1.4749585 | N39: =O39-15 -> 8.2038983 | O39: =VLOOKUP(B39,'Table 1'!$A$8:$G$99,7,FALSE) -> 23.203898
... A47: ZW | B47: Togo | C47: 3.8888887 | D47: 3.4 | E47: 3.5 | F47: 3.5253333 | G47: 9.053799 | H47: 1030 | J47: =(F47^3)*(H47^-0.125)*G47 -> 166.65822 | L47: =IF(ISERROR(J47),"",J47/N47) -> 0.79746247 | N47: =O47-15 -> 208.98566 | O47: =VLOOKUP(B47,'Table 1'!$A$8:$G$99,7,FALSE) -> 223.98566
B48: East Asia and the Pacific | J48: =(F48^3)*(H48^-0.125)*G48 -> #DIV/0! | L48: =IF(ISERROR(J48),"",J48/N48) | N48: =O48-15 -> -15 | O48: =VLOOKUP(B48,'Table 1'!$A$8:$G$99,7,FALSE) -> 0
A49: KH | B49: Cambodia | C49: 3.8222223 | D49: 2.8 | E49: 3.5 | F49: 3.1013334 | G49: 16.944826 | H49: 1810 | J49: =(F49^3)*(H49^-0.125)*G49 -> 197.91224 | L49: =IF(ISERROR(J49),"",J49/N49) -> 1.4749585 | N49: =O49-15 -> 134.18157 | O49: =VLOOKUP(B49,'Table 1'!$A$8:$G$99,7,FALSE) -> 149.18157
A50: FJ | B50: Fiji | C50: 3.5444447 | D50: 3.2 | E50: 3.5 | F50: 3.3066667 | G50: 0.936375 | H50: 5580 | J50: =(F50^3)*(H50^-0.125)*G50 -> 11.515739 | L50: =IF(ISERROR(J50),"",J50/N50) -> 1.4749585 | N50: =O50-15 -> 7.8075004 | O50: =VLOOKUP(B50,'Table 1'!$A$8:$G$99,7,FALSE) -> 22.8075
A51: KI | B51: Kiribati | C51: 2.8444447 | D51: 3.2 | E51: 3 | F51: 3.0986667 | G51: 0.133515 | H51: 3730 | J51: =(F51^3)*(H51^-0.125)*G51 -> 1.4209901 | L51: =IF(ISERROR(J51),"",J51/N51) -> 1.4749585 | N51: =O51-15 -> 0.96341026 | O51: =VLOOKUP(B51,'Table 1'!$A$8:$G$99,7,FALSE) -> 15.96341
A52: LA | B52: Lao People's Democratic Republic | C52: 3.0444443 | D52: 2.8 | E52: 3.5 | F52: 2.9146666 | G52: 7.633779 | H52: 2120 | J52: =(F52^3)*(H52^-0.125)*G52 -> 72.56284 | L52: =IF(ISERROR(J52),"",J52/N52) -> 1.4749585 | N52: =O52-15 -> 49.196531 | O52: =VLOOKUP(B52,'Table 1'!$A$8:$G$99,7,FALSE) -> 64.196531
A53: MH | B53: Marshall Islands | C53: 2.6 | D53: 2.8 | E53: 2.5 | F53: 2.728 | G53: 0.041996 | H53: 7570 | J53: =(F53^3)*(H53^-0.125)*G53 -> 0.27916055 | L53: =IF(ISERROR(J53),"",J53/N53) -> 1.4749585 | N53: =O53-15 -> 0.18926672 | O53: =VLOOKUP(B53,'Table 1'!$A$8:$G$99,7,FALSE) -> 15.189267
A54: FM | B54: Micronesia, Federated States of | C54: 2.7333333 | D54: 2.9 | E54: 3 | F54: 2.868 | G54: 0.115224 | H54: 4150 | J54: =(F54^3)*(H54^-0.125)*G54 -> 0.95945448 | L54: =IF(ISERROR(J54),"",J54/N54) -> 1.4749585 | N54: =O54-15 -> 0.65049593 | O54: =VLOOKUP(B54,'Table 1'!$A$8:$G$99,7,FALSE) -> 15.650496
A55: MM | B55: Myanmar | C55: 2.011111 | D55: 1.9 | E55: 4.5 | F55: 2.1346666 | G55: 54.577997 | H55: 1210 | J55: =(F55^3)*(H55^-0.125)*G55 -> 218.60476 | L55: =IF(ISERROR(J55),"",J55/N55) -> 8.4721668 | N55: =O55-15 -> 25.802698 | O55: =VLOOKUP(B55,'Table 1'!$A$8:$G$99,7,FALSE) -> 40.802698
A56: PG | B56: Papua New Guinea | C56: 2.8666667 | D56: 2.8 | E56: 2.5 | F56: 2.792 | G56: 10.329931 | H56: 2840 | J56: =(F56^3)*(H56^-0.125)*G56 -> 83.210641 | L56: =IF(ISERROR(J56),"",J56/N56) -> 1.4749585 | N56: =O56-15 -> 56.415583 | O56: =VLOOKUP(B56,'Table 1'!$A$8:$G$99,7,FALSE) -> 71.415583
A57: WS | B57: Samoa | C57: 3.9111113 | D57: 4.1 | E57: 3 | F57: 3.9666667 | G57: 0.225681 | H57: 4020 | J57: =(F57^3)*(H57^-0.125)*G57 -> 4.9916472 | L57: =IF(ISERROR(J57),"",J57/N57) -> 1.4749585 | N57: =O57-15 -> 3.3842629 | O57: =VLOOKUP(B57,'Table 1'!$A$8:$G$99,7,FALSE) -> 18.384263
A58: SB | B58: Solomon Islands | C58: 2.988889 | D58: 2.7 | E58: 3.5 | F58: 2.8333334 | G58: 0.740424 | H58: 2270 | J58: =(F58^3)*(H58^-0.125)*G58 -> 6.4101808 | L58: =IF(ISERROR(J58),"",J58/N58) -> 1.4749585 | N58: =O58-15 -> 4.3460077 | O58: =VLOOKUP(B58,'Table 1'!$A$8:$G$99,7,FALSE) -> 19.346008
A59: TP | B59: Timor-Leste | C59: 2.8555553 | D59: 2.6 | E59: 2.5 | F59: 2.6533333 | G59: 1.360596 | H59: 2140 | J59: =(F59^3)*(H59^-0.125)*G59 -> 9.7454721 | L59: =IF(ISERROR(J59),"",J59/N59) -> 1.4749585 | N59: =O59-15 -> 6.6072858 | O59: =VLOOKUP(B59,'Table 1'!$A$8:$G$99,7,FALSE) -> 21.607286
A60: TO | B60: Tonga | C60: 3.411111 | D60: 3.6 | E60: 2.5 | F60: 3.4666666 | G60: 0.107773 | H60: na | J60: =(F60^3)*(H60^-0.125)*G60 -> #VALUE! | L60: =IF(ISERROR(J60),"",J60/N60) | N60: =O60-15 -> 1.046155 | O60: =VLOOKUP(B60,'Table 1'!$A$8:$G$99,7,FALSE) -> 16.046155
A61: TV | B61: Tuvalu | C61: 2.7444447 | D61: 3.2 | E61: 3 | F61: 3.0746667 | G61: 0.011396 | H61: 7550 | J61: =(F61^3)*(H61^-0.125)*G61 -> 0.10849337 | L61: =IF(ISERROR(J61),"",J61/N61) -> 1.4749585 | N61: =O61-15 -> 0.073556901 | O61: =VLOOKUP(B61,'Table 1'!$A$8:$G$99,7,FALSE) -> 15.073557
A62: VU | B62: Vanuatu | C62: 3.3666667 | D62: 3.1 | E62: 4 | F62: 3.236 | G62: 0.334506 | H62: 3660 | J62: =(F62^3)*(H62^-0.125)*G62 -> 4.0643801 | L62: =IF(ISERROR(J62),"",J62/N62) -> 1.4749585 | N62: =O62-15 -> 2.7555895 | O62: =VLOOKUP(B62,'Table 1'!$A$8:$G$99,7,FALSE) -> 17.75559
B63: Europe and Central Asia | J63: =(F63^3)*(H63^-0.125)*G63 -> #DIV/0! | L63: =IF(ISERROR(J63),"",J63/N63) | N63: =O63-15 -> -15 | O63: =VLOOKUP(B63,'Table 1'!$A$8:$G$99,7,FALSE) -> 0
A64: XK | B64: Kosovo | C64: 3.9111113 | D64: 3.5 | E64: 3.5 | F64: 3.5986667 | G64: 1.756374 | H64: 5980 | J64: =(F64^3)*(H64^-0.125)*G64 -> 27.60287 | L64: =IF(ISERROR(J64),"",J64/N64) -> 1.4749585 | N64: =O64-15 -> 18.714337 | O64: =VLOOKUP(B64,'Table 1'!$A$8:$G$99,7,FALSE) -> 33.714337
A65: KG | B65: Kyrgyz Republic | C65: 3.7666667 | D65: 3 | E65: 3.5 | F65: 3.224 | G65: 7.1008 | H65: 1700 | J65: =(F65^3)*(H65^-0.125)*G65 -> 93.90447 | L65: =IF(ISERROR(J65),"",J65/N65) -> 1.4749585 | N65: =O65-15 -> 63.66584 | O65: =VLOOKUP(B65,'Table 1'!$A$8:$G$99,7,FALSE) -> 78.66584
A66: TJ | B66: Tajikistan | C66: 3.222222 | D66: 3.1 | E66: 3 | F66: 3.1213333 | G66: 10.143543 | H66: 1440 | J66: =(F66^3)*(H66^-0.125)*G66 -> 124.28388 | L66: =IF(ISERROR(J66),"",J66/N66) -> 1.4749585 | N66: =O66-15 -> 84.262628 | O66: =VLOOKUP(B66,'Table 1'!$A$8:$G$99,7,FALSE) -> 99.262628
A67: UZ | B67: Uzbekistan | C67: 3.888889 | D67: 3.7 | E67: 3 | F67: 3.6893334 | G67: 36.41235 | H67: 2360 | J67: =(F67^3)*(H67^-0.125)*G67 -> 692.59349 | L67: =IF(ISERROR(J67),"",J67/N67) -> 1.4749585 | N67: =O67-15 -> 469.56813 | O67: =VLOOKUP(B67,'Table 1'!$A$8:$G$99,7,FALSE) -> 484.56813
B68: Latin America and the Caribbean | J68: =(F68^3)*(H68^-0.125)*G68 -> #DIV/0! | L68: =IF(ISERROR(J68),"",J68/N68) | N68: =O68-15 -> -15 | O68: =VLOOKUP(B68,'Table 1'!$A$8:$G$99,7,FALSE) -> 0
B69: Belize | C69: na | D69: na | E69: na | F69: na | G69: 0.410825 | H69: 7190 | J69: =(F69^3)*(H69^-0.125)*G69 -> #VALUE! | L69: =IF(ISERROR(J69),"",J69/N69) | N69: =O69-15 -> 2.5125783 | O69: =VLOOKUP(B69,'Table 1'!$A$8:$G$99,7,FALSE) -> 17.512578
A70: DM | B70: Dominica | C70: 3.6333333 | D70: 3.7 | E70: 3.5 | F70: 3.668 | G70: 0.07304 | H70: 8920 | J70: =(F70^3)*(H70^-0.125)*G70 -> 1.1562537 | L70: =IF(ISERROR(J70),"",J70/N70) -> 1.4749585 | N70: =O70-15 -> 0.78392289 | O70: =VLOOKUP(B70,'Table 1'!$A$8:$G$99,7,FALSE) -> 15.783923
A71: GD | B71: Grenada | C71: 3.8 | D71: 3.5 | E71: 3.5 | F71: 3.572 | G71: 0.126183 | H71: 9800 | J71: =(F71^3)*(H71^-0.125)*G71 -> 1.82319 | L71: =IF(ISERROR(J71),"",J71/N71) -> 1.4749585 | N71: =O71-15 -> 1.2360959 | O71: =VLOOKUP(B71,'Table 1'!$A$8:$G$99,7,FALSE) -> 16.236096
A72: GY | B72: Guyana | C72: 3.3222223 | D72: 3.2 | E72: 3.5 | F72: 3.2533334 | G72: 0.813834 | H72: 20360 | J72: =(F72^3)*(H72^-0.125)*G72 -> 8.1081973 | L72: =IF(ISERROR(J72),"",J72/N72) -> 1.4749585 | N72: =O72-15 -> 5.4972377 | O72: =VLOOKUP(B72,'Table 1'!$A$8:$G$99,7,FALSE) -> 20.497238
A73: HT | B73: Haiti | C73: 2.3222223 | D73: 1.9 | E73: 3 | F73: 2.0893334 | G73: 11.724763 | H73: 1740 | J73: =(F73^3)*(H73^-0.125)*G73 -> 42.078343 | L73: =IF(ISERROR(J73),"",J73/N73) -> 0.86096001 | N73: =O73-15 -> 48.873749 | O73: =VLOOKUP(B73,'Table 1'!$A$8:$G$99,7,FALSE) -> 63.873749
A74: HN | B74: Honduras | C74: 3.4444443 | D74: 2.8 | E74: 2.5 | F74: 2.9306666 | G74: 10.593798 | H74: 2900 | J74: =(F74^3)*(H74^-0.125)*G74 -> 98.435375 | L74: =IF(ISERROR(J74),"",J74/N74) -> 1.4749585 | N74: =O74-15 -> 66.737727 | O74: =VLOOKUP(B74,'Table 1'!$A$8:$G$99,7,FALSE) -> 81.737727
A75: NI | B75: Nicaragua | C75: 3.5 | D75: 2.4 | E75: 4.5 | F75: 2.832 | G75: 7.04631 | H75: 2270 | J75: =(F75^3)*(H75^-0.125)*G75 -> 60.916965 | L75: =IF(ISERROR(J75),"",J75/N75) -> 1.4749585 | N75: =O75-15 -> 41.300801 | O75: =VLOOKUP(B75,'Table 1'!$A$8:$G$99,7,FALSE) -> 56.300801
A76: LC | B76: St. Lucia | C76: 3.688889 | D76: 3.8 | E76: 4.5 | F76: 3.8293334 | G76: 0.180251 | H76: 12400 | J76: =(F76^3)*(H76^-0.125)*G76 -> 3.1157995 | L76: =IF(ISERROR(J76),"",J76/N76) -> 1.4749585 | N76: =O76-15 -> 2.1124659 | O76: =VLOOKUP(B76,'Table 1'!$A$8:$G$99,7,FALSE) -> 17.112466
A77: VC | B77: St. Vincent and the Grenadines | C77: 3.6444447 | D77: 3.7 | E77: 4 | F77: 3.7106667 | G77: 0.103698 | H77: 10070 | J77: =(F77^3)*(H77^-0.125)*G77 -> 1.6739695 | L77: =IF(ISERROR(J77),"",J77/N77) -> 1.4749585 | N77: =O77-15 -> 1.1349265 | O77: =VLOOKUP(B77,'Table 1'!$A$8:$G$99,7,FALSE) -> 16.134927
B78: Suriname | C78: na | D78: na | E78: na | F78: na | G78: 0.623236 | H78: 5360 | J78: =(F78^3)*(H78^-0.125)*G78 -> #VALUE! | L78: =IF(ISERROR(J78),"",J78/N78) | N78: =O78-15 -> 1.9965902 | O78: =VLOOKUP(B78,'Table 1'!$A$8:$G$99,7,FALSE) -> 16.99659
B79: Middle East and North Africa | J79: =(F79^3)*(H79^-0.125)*G79 -> #DIV/0! | L79: =IF(ISERROR(J79),"",J79/N79) | N79: =O79-15 -> -15 | O79: =VLOOKUP(B79,'Table 1'!$A$8:$G$99,7,FALSE) -> 0
A80: DJ | B80: Djibouti | C80: 3.1333333 | D80: 3.1 | E80: 4 | F80: 3.18 | G80: 1.136455 | H80: 3450 | J80: =(F80^3)*(H80^-0.125)*G80 -> 13.200981 | L80: =IF(ISERROR(J80),"",J80/N80) -> 1.4749585 | N80: =O80-15 -> 8.9500699 | O80: =VLOOKUP(B80,'Table 1'!$A$8:$G$99,7,FALSE) -> 23.95007
A81: SY | B81: Syria | C81: na | D81: na | E81: na | F81: na | G81: 23.227014 | H81: na | J81: =(F81^3)*(H81^-0.125)*G81 -> #VALUE! | L81: =IF(ISERROR(J81),"",J81/N81) | N81: =O81-15 -> 92.7 | O81: =VLOOKUP(B81,'Table 1'!$A$8:$G$99,7,FALSE) -> 107.7
A82: RY | B82: Yemen, Republic of | C82: 1.9555557 | D82: 1.5 | E82: 3.5 | F82: 1.7693334 | G82: 34.449825 | H82: na | J82: =(F82^3)*(H82^-0.125)*G82 -> #VALUE! | L82: =IF(ISERROR(J82),"",J82/N82) | N82: =O82-15 -> 115.50878 | O82: =VLOOKUP(B82,'Table 1'!$A$8:$G$99,7,FALSE) -> 130.50878
B83: South Asia | J83: =(F83^3)*(H83^-0.125)*G83 -> #DIV/0! | L83: =IF(ISERROR(J83),"",J83/N83) | N83: =O83-15 -> -15 | O83: =VLOOKUP(B83,'Table 1'!$A$8:$G$99,7,FALSE) -> 0
A84: AF | B84: Afghanistan | C84: 1.677778 | D84: 1.6 | E84: 2.5 | F84: 1.6906667 | G84: 42.239854 | H84: na | J84: =(F84^3)*(H84^-0.125)*G84 -> #VALUE! | L84: =IF(ISERROR(J84),"",J84/N84) | N84: =O84-15 -> 65.863329 | O84: =VLOOKUP(B84,'Table 1'!$A$8:$G$99,7,FALSE) -> 80.863329
A85: BD | B85: Bangladesh | C85: 3.2555553 | D85: 2.7 | E85: 3.5 | F85: 2.8973333 | G85: 172.95432 | H85: 2860 | J85: =(F85^3)*(H85^-0.125)*G85 -> 1555.5394 | L85: =IF(ISERROR(J85),"",J85/N85) -> 1.4749585 | N85: =O85-15 -> 1054.6327 | O85: =VLOOKUP(B85,'Table 1'!$A$8:$G$99,7,FALSE) -> 1069.6327
A86: BT | B86: Bhutan | C86: 3.6666667 | D86: 4 | E86: 3.5 | F86: 3.88 | G86: 0.787424 | H86: na | J86: =(F86^3)*(H86^-0.125)*G86 -> #VALUE! | L86: =IF(ISERROR(J86),"",J86/N86) | N86: =O86-15 -> 11.166031 | O86: =VLOOKUP(B86,'Table 1'!$A$8:$G$99,7,FALSE) -> 26.166031
A87: MV | B87: Maldives | C87: 3.0777777 | D87: 3.2 | E87: 3 | F87: 3.1546666 | G87: 0.521021 | H87: 11030 | J87: =(F87^3)*(H87^-0.125)*G87 -> 5.1096801 | L87: =IF(ISERROR(J87),"",J87/N87) -> 1.4749585 | N87: =O87-15 -> 3.4642874 | O87: =VLOOKUP(B87,'Table 1'!$A$8:$G$99,7,FALSE) -> 18.464287
A88: NP | B88: Nepal | C88: 3.5555553 | D88: 2.8 | E88: 3 | F88: 2.9973333 | G88: 30.89659 | H88: 1370 | J88: =(F88^3)*(H88^-0.125)*G88 -> 337.30718 | L88: =IF(ISERROR(J88),"",J88/N88) -> 1.4749585 | N88: =O88-15 -> 228.68927 | O88: =VLOOKUP(B88,'Table 1'!$A$8:$G$99,7,FALSE) -> 243.68927
B89: Pakistan | C89: 3.3444447 | D89: 3.2 | E89: 3.5 | F89: 3.2586667 | G89: 240.48566 | H89: 1500 | J89: =(F89^3)*(H89^-0.125)*G89 -> 3335.7816 | L89: =IF(ISERROR(J89),"",J89/N89) -> 3.3020134 | N89: =O89-15 -> 1010.2265 | O89: =VLOOKUP(B89,'Table 1'!$A$8:$G$99,7,FALSE) -> 1025.2265
A90: PK | B90: Sri Lanka | C90: 3.0666667 | D90: 3.3 | E90: 3.5 | F90: 3.26 | G90: 22.037 | H90: 3540 | J90: =(F90^3)*(H90^-0.125)*G90 -> 274.90324 | L90: =IF(ISERROR(J90),"",J90/N90) -> 1.4749585 | M90: s | N90: =O90-15 -> 186.38033 | O90: =VLOOKUP(B90,'Table 1'!$A$8:$G$99,7,FALSE) -> 201.38033
B92: Notes:
B93: a/ The CPR is calculated as 0.24 x CPIA (A, B, and C) + 0.68 x CPIA (D) + 0.08 x PPR. For details on the CPR formula, see Annex 3 of See IDA20 Replenishment Report “Building Back Better from the Crisis: Toward a Green, Resilient and Inclusive Future.” "NA" signifies that the country's CPIA was either not available (Syrian Arab Republic) or not disclosed at the time of allocations as a country was an IBRD-only as the time of an assessment.
B95: b/ The source for the population and GNI per capita data is the Development Economics Data Group (DECDG). Per capita data shown for 2023 are either actual figures or, when actual figures were not available, estimates as of June 2024, when IDA country allocations for FY25 were determined. “NA” signifies countries for which data estimates were available in ranges only per earlier disclosure under Annex 2 of Bank Directive "Financial Terms and Conditions of Bank Financing" for FY25.
B97: c/ Eritrea and Zimbabwe are inactive IDA countries with credits in non-accrual status. Syrian Arab Republic has been removed from the list of countries with loans/credits in nonaccrual status, effective May 12, 2025.

Sheet forR
A1: country | B1: CPIA_ave_abc | C1: CPIA_D | D1: PPR | E1: CPR | F1: pop | G1: gnipc | H1: allocation
A2: Burundi | B2: 3.2888887 | C2: 2.4 | D2: 3.5 | E2: 2.7013333 | F2: 13.238559 | G2: 230 | H2: 183.14803
A3: Comoros | B3: 2.8555557 | C3: 2.1 | D3: 3.5 | E3: 2.3933334 | F3: 0.852075 | G3: 1600 | H3: 18.149145
A4: Congo, Democratic Republic of | B4: 3.3666667 | C4: 2.6 | D4: 3.5 | E4: 2.856 | F4: 102.26281 | G4: 660 | H4: 732.41349
A5: Eritrea | B5: 1.7555557 | C5: 1.5 | D5: na | E5: 1.5817778 | F5: 3.748901 | G5: na | H5: 0
A6: Eswatini | B6: na | C6: na | D6: na | E6: na | F6: 1.210822 | G6: 3860 | H6: 20.795188
A7: Ethiopia | B7: 3.1666667 | C7: 3.1 | D7: 4 | E7: 3.188 | F7: 126.52706 | G7: 1130 | H7: 1169.3135
A8: Kenya | B8: 3.911111 | C8: 3.6 | D8: 3 | E8: 3.6266666 | F8: 55.100586 | G8: 2110 | H8: 699.48515
A9: Lesotho | B9: 3.388889 | C9: 2.9 | D9: 3 | E9: 3.0253334 | F9: 2.330318 | G9: 1160 | H9: 33.109141
A10: Madagascar | B10: 3.4333333 | C10: 2.7 | D10: 3.5 | E10: 2.94 | F10: 30.325732 | G10: 530 | H10: 253.5278
A11: Malawi | B11: 3.0333333 | C11: 3 | D11: 3.5 | E11: 3.048 | F11: 20.931751 | G11: 640 | H11: 194.18356
A12: Mozambique | B12: 3.2111113 | C12: 2.9 | D12: 3 | E12: 2.9826667 | F12: 33.897354 | G12: 530 | H12: 456.64325
A13: Rwanda | B13: 4.188889 | C13: 3.9 | D13: 3.5 | E13: 3.9373334 | F13: 14.094683 | G13: 980 | H13: 261.59191
A14: Sao Tome and Principe | B14: 2.9 | C14: 3 | D14: 3.5 | E14: 3.016 | F14: 0.231856 | G14: 2480 | H14: 16.623402
A15: Somalia | B15: 2.3333333 | C15: 1.9 | D15: 4 | E15: 2.172 | F15: 18.143378 | G15: 610 | H15: 227.73791
A16: South Sudan | B16: 1.788889 | C16: 1.3 | D16: 3.5 | E16: 1.5933334 | F16: 11.088796 | G16: na | H16: 71.482788
A17: Sudan | B17: 2.0666667 | C17: 1.8 | D17: 4 | E17: 2.04 | F17: 48.109006 | G17: 990 | H17: 131.91835
A18: Tanzania | B18: 3.6444447 | C18: 3.1 | D18: 3.5 | E18: 3.2626667 | F18: 65.36289 | G18: 1210 | H18: 648.75504
A19: Uganda | B19: 3.6333333 | C19: 3.3 | D19: 3 | E19: 3.356 | F19: 48.582334 | G19: 980 | H19: 541.3337
A20: Zambia | B20: 3.3555553 | C20: 2.9 | D20: 3.5 | E20: 3.0573333 | F20: 20.569737 | G20: 1320 | H20: 177.33253
A21: Zimbabwe | B21: 3.011111 | C21: 2.9 | D21: 4.5 | E21: 3.0546666 | F21: 16.665409 | G21: 1740 | H21: 0
A22: Benin | B22: 3.9666667 | C22: 3.7 | D22: 4 | E22: 3.788 | F22: 13.712828 | G22: 1440 | H22: 381.84741
A23: Burkina Faso | B23: 3.5 | C23: 3.2 | D23: 3.5 | E23: 3.296 | F23: 23.251485 | G23: 850 | H23: 257.91546
A24: Cameroon | B24: 3.4333333 | C24: 3 | D24: 3 | E24: 3.104 | F24: 28.647293 | G24: 1650 | H24: 245.08242
A25: Cape Verde | B25: 3.8333333 | C25: 4 | D25: 3.5 | E25: 3.92 | F25: 0.598682 | G25: 4280 | H25: 23.596945
A26: Central African Republic | B26: 2.6555557 | C26: 2.4 | D26: 4 | E26: 2.5893334 | F26: 5.742315 | G26: 470 | H26: 46.322678
A27: Chad | B27: 2.8 | C27: 2.4 | D27: 3 | E27: 2.544 | F27: 18.278568 | G27: 710 | H27: 157.20933
A28: Congo, Republic of | B28: 2.888889 | C28: 2.8 | D28: 3 | E28: 2.8373334 | F28: 6.106869 | G28: 2470 | H28: 50.619087
... A52: Timor-Leste | B52: 2.8555553 | C52: 2.6 | D52: 2.5 | E52: 2.6533333 | F52: 1.360596 | G52: 2140 | H52: 21.607286
A53: Tonga | B53: 3.411111 | C53: 3.6 | D53: 2.5 | E53: 3.4666666 | F53: 0.107773 | G53: na | H53: 16.046155
A54: Tuvalu | B54: 2.7444447 | C54: 3.2 | D54: 3 | E54: 3.0746667 | F54: 0.011396 | G54: 7550 | H54: 15.073557
A55: Vanuatu | B55: 3.3666667 | C55: 3.1 | D55: 4 | E55: 3.236 | F55: 0.334506 | G55: 3660 | H55: 17.75559
A56: Kosovo | B56: 3.9111113 | C56: 3.5 | D56: 3.5 | E56: 3.5986667 | F56: 1.756374 | G56: 5980 | H56: 33.714337
A57: Kyrgyz Republic | B57: 3.7666667 | C57: 3 | D57: 3.5 | E57: 3.224 | F57: 7.1008 | G57: 1700 | H57: 78.66584
A58: Tajikistan | B58: 3.222222 | C58: 3.1 | D58: 3 | E58: 3.1213333 | F58: 10.143543 | G58: 1440 | H58: 99.262628
A59: Uzbekistan | B59: 3.888889 | C59: 3.7 | D59: 3 | E59: 3.6893334 | F59: 36.41235 | G59: 2360 | H59: 484.56813
A60: Belize | B60: na | C60: na | D60: na | E60: na | F60: 0.410825 | G60: 7190 | H60: 17.512578
A61: Dominica | B61: 3.6333333 | C61: 3.7 | D61: 3.5 | E61: 3.668 | F61: 0.07304 | G61: 8920 | H61: 15.783923
A62: Grenada | B62: 3.8 | C62: 3.5 | D62: 3.5 | E62: 3.572 | F62: 0.126183 | G62: 9800 | H62: 16.236096
A63: Guyana | B63: 3.3222223 | C63: 3.2 | D63: 3.5 | E63: 3.2533334 | F63: 0.813834 | G63: 20360 | H63: 20.497238
A64: Haiti | B64: 2.3222223 | C64: 1.9 | D64: 3 | E64: 2.0893334 | F64: 11.724763 | G64: 1740 | H64: 63.873749
A65: Honduras | B65: 3.4444443 | C65: 2.8 | D65: 2.5 | E65: 2.9306666 | F65: 10.593798 | G65: 2900 | H65: 81.737727
A66: Nicaragua | B66: 3.5 | C66: 2.4 | D66: 4.5 | E66: 2.832 | F66: 7.04631 | G66: 2270 | H66: 56.300801
A67: St. Lucia | B67: 3.688889 | C67: 3.8 | D67: 4.5 | E67: 3.8293334 | F67: 0.180251 | G67: 12400 | H67: 17.112466
A68: St. Vincent and the Grenadines | B68: 3.6444447 | C68: 3.7 | D68: 4 | E68: 3.7106667 | F68: 0.103698 | G68: 10070 | H68: 16.134927
A69: Suriname | B69: na | C69: na | D69: na | E69: na | F69: 0.623236 | G69: 5360 | H69: 16.99659
A70: Djibouti | B70: 3.1333333 | C70: 3.1 | D70: 4 | E70: 3.18 | F70: 1.136455 | G70: 3450 | H70: 23.95007
A71: Syria | B71: na | C71: na | D71: na | E71: na | F71: 23.227014 | G71: na | H71: 107.7
A72: Yemen, Republic of | B72: 1.9555557 | C72: 1.5 | D72: 3.5 | E72: 1.7693334 | F72: 34.449825 | G72: na | H72: 130.50878
A73: Afghanistan | B73: 1.677778 | C73: 1.6 | D73: 2.5 | E73: 1.6906667 | F73: 42.239854 | G73: na | H73: 80.863329
A74: Bangladesh | B74: 3.2555553 | C74: 2.7 | D74: 3.5 | E74: 2.8973333 | F74: 172.95432 | G74: 2860 | H74: 1069.6327
A75: Bhutan | B75: 3.6666667 | C75: 4 | D75: 3.5 | E75: 3.88 | F75: 0.787424 | G75: na | H75: 26.166031
A76: Maldives | B76: 3.0777777 | C76: 3.2 | D76: 3 | E76: 3.1546666 | F76: 0.521021 | G76: 11030 | H76: 18.464287
A77: Nepal | B77: 3.5555553 | C77: 2.8 | D77: 3 | E77: 2.9973333 | F77: 30.89659 | G77: 1370 | H77: 243.68927
A78: Pakistan | B78: 3.3444447 | C78: 3.2 | D78: 3.5 | E78: 3.2586667 | F78: 240.48566 | G78: 1500 | H78: 1025.2265
A79: Sri Lanka | B79: 3.0666667 | C79: 3.3 | D79: 3.5 | E79: 3.26 | F79: 22.037 | G79: 3540 | H79: 201.38033
